LICENSE
greynirseq/__init__.py
greynirseq/cli/__init__.py
greynirseq/cli/greynirseq_main.py
greynirseq/ner/README.md
greynirseq/ner/__init__.py
greynirseq/ner/aligner.py
greynirseq/ner/ner_f1_stats.py
greynirseq/ner/nertagger.py
greynirseq/ner/patcher.py
greynirseq/ner/postagger.py
greynirseq/ner/testdata/en_is.tsv
greynirseq/ner/testdata/names.txt
greynirseq/nicenlp/__init__.py
greynirseq/nicenlp/criterions/__init__.py
greynirseq/nicenlp/criterions/multi_span_prediction_criterion.py
greynirseq/nicenlp/criterions/multiclass_token_classification_criterion.py
greynirseq/nicenlp/criterions/multilabel_token_classification_criterion.py
greynirseq/nicenlp/criterions/parser_criterion.py
greynirseq/nicenlp/data/__init__.py
greynirseq/nicenlp/data/datasets.py
greynirseq/nicenlp/data/encoding.py
greynirseq/nicenlp/data/lazymmapdataset.py
greynirseq/nicenlp/data/lookup_dataset.py
greynirseq/nicenlp/data/mutex_binary_dataset.py
greynirseq/nicenlp/data/tests.py
greynirseq/nicenlp/examples/constituency_parsing/Dockerfile
greynirseq/nicenlp/examples/constituency_parsing/README.md
greynirseq/nicenlp/examples/constituency_parsing/encode_data.py
greynirseq/nicenlp/examples/constituency_parsing/finetune.sh
greynirseq/nicenlp/examples/constituency_parsing/infer_file.sh
greynirseq/nicenlp/examples/constituency_parsing/predict_file.py
greynirseq/nicenlp/examples/constituency_parsing/prepare_data.sh
greynirseq/nicenlp/examples/constituency_parsing/pretrain.sh
greynirseq/nicenlp/examples/ner/README.md
greynirseq/nicenlp/examples/ner/ner_train.sh
greynirseq/nicenlp/examples/ner/predict_ner.py
greynirseq/nicenlp/examples/ner/train.sh
greynirseq/nicenlp/examples/pos/README.md
greynirseq/nicenlp/examples/pos/labdict.txt
greynirseq/nicenlp/examples/pos/prep_mim_pos.sh
greynirseq/nicenlp/examples/pos/terms.json
greynirseq/nicenlp/examples/pos/train.sh
greynirseq/nicenlp/examples/translation/README.md
greynirseq/nicenlp/models/__init__.py
greynirseq/nicenlp/models/bart.py
greynirseq-0.4.dist-info/entry_points.txt
greynirseq-0.4.dist-info/LICENSE
greynirseq-0.4.dist-info/WHEEL
greynirseq-0.4.dist-info/METADATA
greynirseq-0.4.dist-info/RECORD
