Metadata-Version: 2.1
Name: greynirseq
Version: 0.4
Summary: Natural language processing for Icelandic
Home-page: https://github.com/mideind/GreynirSeq
License: AGPLv3+
Keywords: nlp,pos,ner,icelandic
Author: Miðeind ehf
Author-email: tauganet@mideind.is
Requires-Python: >=3.7.2,<4.0.0
Classifier: Development Status :: 4 - Beta
Classifier: Environment :: GPU :: NVIDIA CUDA :: 10.1
Classifier: Environment :: GPU :: NVIDIA CUDA :: 10.2
Classifier: Environment :: GPU :: NVIDIA CUDA :: 11.0
Classifier: Environment :: GPU :: NVIDIA CUDA :: 11.1
Classifier: Intended Audience :: Developers
Classifier: License :: OSI Approved :: GNU Affero General Public License v3 or later (AGPLv3+)
Classifier: License :: Other/Proprietary License
Classifier: Natural Language :: Icelandic
Classifier: Operating System :: POSIX
Classifier: Operating System :: Unix
Classifier: Programming Language :: Cython
Classifier: Programming Language :: Python
Classifier: Programming Language :: Python :: 3
Classifier: Programming Language :: Python :: 3.6
Classifier: Programming Language :: Python :: 3.7
Classifier: Programming Language :: Python :: 3.8
Classifier: Programming Language :: Python :: 3.9
Classifier: Topic :: Scientific/Engineering :: Artificial Intelligence
Classifier: Topic :: Software Development :: Libraries :: Python Modules
Classifier: Topic :: Text Processing :: Linguistic
Classifier: Topic :: Utilities
Requires-Dist: editdistance (>=0.6.0,<0.7.0)
Requires-Dist: fairseq (>=0.10.0,<0.11.0)
Requires-Dist: langid (>=1.1.6,<2.0.0)
Requires-Dist: nltk (>=3.5,<4.0)
Requires-Dist: pyjarowinkler (>=1.8,<2.0)
Requires-Dist: reynir (>=3.5.0,<4.0.0)
Requires-Dist: scipy (>=1.5,<2.0)
Requires-Dist: sentencepiece (>=0.1.96,<0.2.0)
Requires-Dist: spacy (>=2,<3)
Requires-Dist: transformers (>=4.3.2,<5.0.0)
Project-URL: Repository, https://github.com/mideind/GreynirSeq
